fastapi_simple_bearer/FSB.py
fastapi_simple_bearer/__init__.py
fastapi_simple_bearer/exceptions.py
fastapi_simple_bearer-0.1.2.dist-info/METADATA
fastapi_simple_bearer-0.1.2.dist-info/WHEEL
fastapi_simple_bearer-0.1.2.dist-info/RECORD
