Metadata-Version: 2.1
Name: fastapi-simple-bearer
Version: 0.1.2
Summary: The simpliest way to secure your API with preset token
Author: Yan Khachko
Author-email: a@slnk.icu
Requires-Python: >=3.10,<4.0
Classifier: Programming Language :: Python :: 3
Classifier: Programming Language :: Python :: 3.10
Classifier: Programming Language :: Python :: 3.11
Classifier: Programming Language :: Python :: 3.12
Requires-Dist: fastapi (>=0.115.0,<0.116.0)
Project-URL: Source, https://github.com/sijokun/async-fastapi-jwt-auth
